django_devops/__init__.py
django_devops/guides/__init__.py
django_devops/guides/auth.py
django_devops/management/__init__.py
django_devops/management/commands/__init__.py
django_devops/management/commands/devops.py
django_devops/management/commands/prep_celery.py
django_devops/management/commands/prep_gunicorn.py
django_devops/management/commands/prep_nginx.py
django_devops/management/commands/update_services.py
django_devops/utils/__init__.py
django_devops/utils/logger.py
django_devops/utils/user_input.py
django_devops-0.2.16.dist-info/LICENSE
django_devops-0.2.16.dist-info/METADATA
django_devops-0.2.16.dist-info/WHEEL
django_devops-0.2.16.dist-info/top_level.txt
django_devops-0.2.16.dist-info/RECORD
